Tool.py
xzz/__init__.py
xzz/xzzone.py
the_way_of_writing_paper-1.0.0.dist-info/LICENSE.txt
the_way_of_writing_paper-1.0.0.dist-info/METADATA
the_way_of_writing_paper-1.0.0.dist-info/WHEEL
the_way_of_writing_paper-1.0.0.dist-info/top_level.txt
the_way_of_writing_paper-1.0.0.dist-info/RECORD
