Metadata-Version: 2.1
Name: the-way-of-writing-paper
Version: 1.0.0
Summary: これは論文の書き方の掟
Home-page: https://github.com/xiaozezhong/Python_code
Author: xzz
Author-email: xiaozz98@yeah.net
License: MIT
Platform: UNKNOWN
